{
  "geoCoordMap": {
    "海门": [
      121.15,
      31.89
    ],
    "鄂尔多斯": [
      109.781327,
      39.608266
    ],
    "招远": [
      120.38,
      37.35
    ],
    "舟山": [
      122.207216,
      29.985295
    ],
    "齐齐哈尔": [
      123.97,
      47.33
    ],
    "盐城": [
      120.13,
      33.38
    ],
    "赤峰": [
      118.87,
      42.28
    ],
    "青岛": [
      120.33,
      36.07
    ],
    "乳山": [
      121.52,
      36.89
    ],
    "金昌": [
      102.188043,
      38.520089
    ],
    "泉州": [
      118.58,
      24.93
    ],
    "莱西": [
      120.53,
      36.86
    ],
    "日照": [
      119.46,
      35.42
    ],
    "胶南": [
      119.97,
      35.88
    ],
    "南通": [
      121.05,
      32.08
    ],
    "拉萨": [
      91.11,
      29.97
    ],
    "云浮": [
      112.02,
      22.93
    ],
    "梅州": [
      116.1,
      24.55
    ],
    "文登": [
      122.05,
      37.2
    ],
    "上海": [
      121.48,
      31.22
    ],
    "攀枝花": [
      101.718637,
      26.582347
    ],
    "威海": [
      122.1,
      37.5
    ],
    "承德": [
      117.93,
      40.97
    ],
    "厦门": [
      118.1,
      24.46
    ],
    "汕尾": [
      115.375279,
      22.786211
    ],
    "潮州": [
      116.63,
      23.68
    ],
    "丹东": [
      124.37,
      40.13
    ],
    "太仓": [
      121.1,
      31.45
    ],
    "曲靖": [
      103.79,
      25.51
    ],
    "烟台": [
      121.39,
      37.52
    ],
    "福州": [
      119.3,
      26.08
    ],
    "瓦房店": [
      121.979603,
      39.627114
    ],
    "即墨": [
      120.45,
      36.38
    ],
    "抚顺": [
      123.97,
      41.97
    ],
    "玉溪": [
      102.52,
      24.35
    ],
    "张家口": [
      114.87,
      40.82
    ],
    "阳泉": [
      113.57,
      37.85
    ],
    "莱州": [
      119.942327,
      37.177017
    ],
    "湖州": [
      120.1,
      30.86
    ],
    "汕头": [
      116.69,
      23.39
    ],
    "昆山": [
      120.95,
      31.39
    ],
    "宁波": [
      121.56,
      29.86
    ],
    "湛江": [
      110.359377,
      21.270708
    ],
    "揭阳": [
      116.35,
      23.55
    ],
    "荣成": [
      122.41,
      37.16
    ],
    "连云港": [
      119.16,
      34.59
    ],
    "葫芦岛": [
      120.836932,
      40.711052
    ],
    "常熟": [
      120.74,
      31.64
    ],
    "东莞": [
      113.75,
      23.04
    ],
    "河源": [
      114.68,
      23.73
    ],
    "淮安": [
      119.15,
      33.5
    ],
    "泰州": [
      119.9,
      32.49
    ],
    "南宁": [
      108.33,
      22.84
    ],
    "营口": [
      122.18,
      40.65
    ],
    "惠州": [
      114.4,
      23.09
    ],
    "江阴": [
      120.26,
      31.91
    ],
    "蓬莱": [
      120.75,
      37.8
    ],
    "韶关": [
      113.62,
      24.84
    ],
    "嘉峪关": [
      98.289152,
      39.77313
    ],
    "广州": [
      113.14,
      23.08
    ],
    "延安": [
      109.47,
      36.6
    ],
    "太原": [
      112.53,
      37.87
    ],
    "清远": [
      113.01,
      23.7
    ],
    "中山": [
      113.38,
      22.52
    ],
    "昆明": [
      102.73,
      25.04
    ],
    "寿光": [
      118.73,
      36.86
    ],
    "盘锦": [
      122.070714,
      41.119997
    ],
    "长治": [
      113.08,
      36.18
    ],
    "深圳": [
      114.07,
      22.62
    ],
    "珠海": [
      113.34,
      22.17
    ],
    "宿迁": [
      118.3,
      33.96
    ],
    "咸阳": [
      108.72,
      34.36
    ],
    "铜川": [
      109.11,
      35.09
    ],
    "平度": [
      119.97,
      36.77
    ],
    "佛山": [
      113.11,
      23.05
    ],
    "海口": [
      110.35,
      20.02
    ],
    "江门": [
      113.06,
      22.61
    ],
    "章丘": [
      117.53,
      36.72
    ],
    "肇庆": [
      112.44,
      23.05
    ],
    "大连": [
      121.62,
      38.92
    ],
    "临汾": [
      111.5,
      36.08
    ],
    "吴江": [
      120.63,
      31.16
    ],
    "石嘴山": [
      106.39,
      39.04
    ],
    "沈阳": [
      123.38,
      41.8
    ],
    "苏州": [
      120.62,
      31.32
    ],
    "茂名": [
      110.88,
      21.68
    ],
    "嘉兴": [
      120.76,
      30.77
    ],
    "长春": [
      125.35,
      43.88
    ],
    "胶州": [
      120.03336,
      36.264622
    ],
    "银川": [
      106.27,
      38.47
    ],
    "张家港": [
      120.555821,
      31.875428
    ],
    "三门峡": [
      111.19,
      34.76
    ],
    "锦州": [
      121.15,
      41.13
    ],
    "南昌": [
      115.89,
      28.68
    ],
    "柳州": [
      109.4,
      24.33
    ],
    "三亚": [
      109.511909,
      18.252847
    ],
    "自贡": [
      104.778442,
      29.33903
    ],
    "吉林": [
      126.57,
      43.87
    ],
    "阳江": [
      111.95,
      21.85
    ],
    "泸州": [
      105.39,
      28.91
    ],
    "西宁": [
      101.74,
      36.56
    ],
    "宜宾": [
      104.56,
      29.77
    ],
    "呼和浩特": [
      111.65,
      40.82
    ],
    "成都": [
      104.06,
      30.67
    ],
    "大同": [
      113.3,
      40.12
    ],
    "镇江": [
      119.44,
      32.2
    ],
    "桂林": [
      110.28,
      25.29
    ],
    "张家界": [
      110.479191,
      29.117096
    ],
    "宜兴": [
      119.82,
      31.36
    ],
    "北海": [
      109.12,
      21.49
    ],
    "西安": [
      108.95,
      34.27
    ],
    "金坛": [
      119.56,
      31.74
    ],
    "东营": [
      118.49,
      37.46
    ],
    "牡丹江": [
      129.58,
      44.6
    ],
    "遵义": [
      106.9,
      27.7
    ],
    "绍兴": [
      120.58,
      30.01
    ],
    "扬州": [
      119.42,
      32.39
    ],
    "常州": [
      119.95,
      31.79
    ],
    "潍坊": [
      119.1,
      36.62
    ],
    "重庆": [
      106.54,
      29.59
    ],
    "台州": [
      121.420757,
      28.656386
    ],
    "南京": [
      118.78,
      32.04
    ],
    "滨州": [
      118.03,
      37.36
    ],
    "贵阳": [
      106.71,
      26.57
    ],
    "无锡": [
      120.29,
      31.59
    ],
    "本溪": [
      123.73,
      41.3
    ],
    "克拉玛依": [
      84.77,
      45.59
    ],
    "渭南": [
      109.5,
      34.52
    ],
    "马鞍山": [
      118.48,
      31.56
    ],
    "宝鸡": [
      107.15,
      34.38
    ],
    "焦作": [
      113.21,
      35.24
    ],
    "句容": [
      119.16,
      31.95
    ],
    "北京": [
      116.46,
      39.92
    ],
    "徐州": [
      117.2,
      34.26
    ],
    "衡水": [
      115.72,
      37.72
    ],
    "包头": [
      110,
      40.58
    ],
    "绵阳": [
      104.73,
      31.48
    ],
    "乌鲁木齐": [
      87.68,
      43.77
    ],
    "枣庄": [
      117.57,
      34.86
    ],
    "杭州": [
      120.19,
      30.26
    ],
    "淄博": [
      118.05,
      36.78
    ],
    "鞍山": [
      122.85,
      41.12
    ],
    "溧阳": [
      119.48,
      31.43
    ],
    "库尔勒": [
      86.06,
      41.68
    ],
    "安阳": [
      114.35,
      36.1
    ],
    "开封": [
      114.35,
      34.79
    ],
    "济南": [
      117,
      36.65
    ],
    "德阳": [
      104.37,
      31.13
    ],
    "温州": [
      120.65,
      28.01
    ],
    "九江": [
      115.97,
      29.71
    ],
    "邯郸": [
      114.47,
      36.6
    ],
    "临安": [
      119.72,
      30.23
    ],
    "兰州": [
      103.73,
      36.03
    ],
    "沧州": [
      116.83,
      38.33
    ],
    "临沂": [
      118.35,
      35.05
    ],
    "南充": [
      106.110698,
      30.837793
    ],
    "天津": [
      117.2,
      39.13
    ],
    "富阳": [
      119.95,
      30.07
    ],
    "泰安": [
      117.13,
      36.18
    ],
    "诸暨": [
      120.23,
      29.71
    ],
    "郑州": [
      113.65,
      34.76
    ],
    "哈尔滨": [
      126.63,
      45.75
    ],
    "聊城": [
      115.97,
      36.45
    ],
    "芜湖": [
      118.38,
      31.33
    ],
    "唐山": [
      118.02,
      39.63
    ],
    "平顶山": [
      113.29,
      33.75
    ],
    "邢台": [
      114.48,
      37.05
    ],
    "德州": [
      116.29,
      37.45
    ],
    "济宁": [
      116.59,
      35.38
    ],
    "荆州": [
      112.239741,
      30.335165
    ],
    "宜昌": [
      111.3,
      30.7
    ],
    "义乌": [
      120.06,
      29.32
    ],
    "丽水": [
      119.92,
      28.45
    ],
    "洛阳": [
      112.44,
      34.7
    ],
    "秦皇岛": [
      119.57,
      39.95
    ],
    "株洲": [
      113.16,
      27.83
    ],
    "石家庄": [
      114.48,
      38.03
    ],
    "莱芜": [
      117.67,
      36.19
    ],
    "常德": [
      111.69,
      29.05
    ],
    "保定": [
      115.48,
      38.85
    ],
    "湘潭": [
      112.91,
      27.87
    ],
    "金华": [
      119.64,
      29.12
    ],
    "岳阳": [
      113.09,
      29.37
    ],
    "长沙": [
      113,
      28.21
    ],
    "衢州": [
      118.88,
      28.97
    ],
    "廊坊": [
      116.7,
      39.53
    ],
    "菏泽": [
      115.480656,
      35.23375
    ],
    "合肥": [
      117.27,
      31.86
    ],
    "武汉": [
      114.31,
      30.52
    ],
    "大庆": [
      125.03,
      46.58
    ],
    "亚信科技（中国）有限公司": [
      104.114129,
      37.550339
    ],
    "株洲中车时代电气股份有限公司": [
      113.131695,
      27.827433
    ],
    "广州佳都集团有限公司": [
      113.378584,
      23.130517
    ],
    "武汉邮电科学研究院": [
      114.397614,
      30.521235
    ],
    "博彦科技股份有限公司": [
      116.304311,
      40.05099
    ],
    "普天信息技术研究院有限公司": [
      116.317132,
      40.040105
    ],
    "上海宝信软件股份有限公司": [
      121.60487,
      31.217393
    ],
    "江苏省通信服务有限公司": [
      118.78979,
      32.026292
    ],
    "北京小米移动软件有限公司": [
      87.68,
      43.77
    ]
  },
  "middleTime": [
    2016
  ],
  "totalValue": [
    [
      {
        "name": "江苏",
        "value": 2981.91
      },
      {
        "name": "广东",
        "value": 3443.77
      },
      {
        "name": "北京",
        "value": 2425.07
      },
      {
        "name": "山东",
        "value": 1441.93
      },
      {
        "name": "上海",
        "value": 1408.20
      },
      {
        "name": "浙江",
        "value": 1563.97
      },
      {
        "name": "四川",
        "value": 857.36
      },
      {
        "name": "辽宁",
        "value": 640.12
      },
      {
        "name": "福建",
        "value": 722.39
      },
      {
        "name": "陕西",
        "value": 613.51
      },
      {
        "name": "湖北",
        "value": 559.65
      },
      {
        "name": "天津",
        "value": 488.97
      },
      {
        "name": "重庆",
        "value": 476.07
      },
      {
        "name": "湖南",
        "value": 102.21
      },
      {
        "name": "吉林",
        "value": 78.16
      },
      {
        "name": "河北",
        "value": 52.58
      },
      {
        "name": "安徽",
        "value": 81.17
      },
      {
        "name": "黑龙江",
        "value": 36.59
      },
      {
        "name": "河南",
        "value": 21.22
      },
      {
        "name": "贵州",
        "value": 50.24
      },
      {
        "name": "广西",
        "value": 38.90
      },
      {
        "name": "江西",
        "value": 23.53
      },
      {
        "name": "海南",
        "value": 37.54
      },
      {
        "name": "新疆",
        "value": 9.78
      },
      {
        "name": "云南",
        "value": 12.60
      },
      {
        "name": "甘肃",
        "value": 8.53
      },
      {
        "name": "内蒙古",
        "value": 4.89
      },
      {
        "name": "山西",
        "value": 4.27
      },
      {
        "name": "宁夏",
        "value": 3.59
      },
      {
        "name": "青海",
        "value": 0.14
      }
    ]
  ],
  "softwarePrduct": [
    [
      {
        "name": "江苏",
        "value": 1956.25
      },
      {
        "name": "北京",
        "value": 1898.10
      },
      {
        "name": "广东",
        "value": 1571.41
      },
      {
        "name": "山东",
        "value": 1446.13
      },
      {
        "name": "上海",
        "value": 1084.60
      },
      {
        "name": "浙江",
        "value": 902.41
      },
      {
        "name": "辽宁",
        "value": 810.51
      },
      {
        "name": "四川",
        "value": 793.57
      },
      {
        "name": "福建",
        "value": 782.15
      },
      {
        "name": "湖北",
        "value": 594.38
      },
      {
        "name": "陕西",
        "value": 361.79
      },
      {
        "name": "天津",
        "value": 269.32
      },
      {
        "name": "重庆",
        "value": 193.27
      },
      {
        "name": "湖南",
        "value": 188.80
      },
      {
        "name": "吉林",
        "value": 94.45
      },
      {
        "name": "安徽",
        "value": 91.61
      },
      {
        "name": "河南",
        "value": 83.15
      },
      {
        "name": "黑龙江",
        "value": 52.13
      },
      {
        "name": "贵州",
        "value": 46.78
      },
      {
        "name": "江西",
        "value": 25.28
      },
      {
        "name": "河北",
        "value": 22.59
      },
      {
        "name": "海南",
        "value": 18.80
      },
      {
        "name": "内蒙古",
        "value": 12.00
      },
      {
        "name": "广西",
        "value": 10.07
      },
      {
        "name": "云南",
        "value": 9.47
      },
      {
        "name": "甘肃",
        "value": 8.25
      },
      {
        "name": "新疆",
        "value": 7.25
      },
      {
        "name": "山西",
        "value": 6.83
      },
      {
        "name": "宁夏",
        "value": 4.14
      }
    ]
  ],
  "informationTechnology": [
    [
      {
        "name": "广东",
        "value": 3476.57
      },
      {
        "name": "北京",
        "value": 3388.55
      },
      {
        "name": "江苏",
        "value": 2987.04
      },
      {
        "name": "浙江",
        "value": 1958.60
      },
      {
        "name": "上海",
        "value": 1953.85
      },
      {
        "name": "山东",
        "value": 1817.38
      },
      {
        "name": "四川",
        "value": 1294.03
      },
      {
        "name": "辽宁",
        "value": 1150.77
      },
      {
        "name": "福建",
        "value": 1115.10
      },
      {
        "name": "陕西",
        "value": 764.86
      },
      {
        "name": "天津",
        "value": 561.03
      },
      {
        "name": "重庆",
        "value": 517.49
      },
      {
        "name": "湖北",
        "value": 505.27
      },
      {
        "name": "吉林",
        "value": 232.49
      },
      {
        "name": "湖南",
        "value": 157.96
      }
    ]
  ],
  "systemSoftware": [
    [
      {
        "name": "江苏",
        "value": 2608.96
      },
      {
        "name": "广东",
        "value": 2102.82
      },
      {
        "name": "山东",
        "value": 664.71
      },
      {
        "name": "浙江",
        "value": 370.29
      },
      {
        "name": "福建",
        "value": 230.45
      },
      {
        "name": "重庆",
        "value": 208.44
      },
      {
        "name": "天津",
        "value": 191.02
      },
      {
        "name": "陕西",
        "value": 125.96
      },
      {
        "name": "上海",
        "value": 120.00
      },
      {
        "name": "辽宁",
        "value": 105.04
      },
      {
        "name": "北京",
        "value": 98.81
      },
      {
        "name": "吉林",
        "value": 93.10
      },
      {
        "name": "湖北",
        "value": 62.40
      },
      {
        "name": "四川",
        "value": 47.82
      },
      {
        "name": "湖南",
        "value": 41.58
      },
      {
        "name": "安徽",
        "value": 24.56
      },
      {
        "name": "黑龙江",
        "value": 14.20
      },
      {
        "name": "河南",
        "value": 11.92
      },
      {
        "name": "河北",
        "value": 9.00
      },
      {
        "name": "山西",
        "value": 1.90
      },
      {
        "name": "江西",
        "value": 1.36
      },
      {
        "name": "宁夏",
        "value": 1.31
      },
      {
        "name": "贵州",
        "value": 0.78
      },
      {
        "name": "广西",
        "value": 0.51
      },
      {
        "name": "新疆",
        "value": 0.43
      },
      {
        "name": "甘肃",
        "value": 0.39
      },
      {
        "name": "云南",
        "value": 0.28
      },
      {
        "name": "内蒙古",
        "value": 0.16
      },
      {
        "name": "海南",
        "value": 0.10
      }
    ]
  ],
  "companyNumber": [
    [
      {
        "name": "北京市",
        "x": [
          116.46,
          39.92
        ],
        "value": 2879
      },
      {
        "name": "天津市",
        "x": [
          117.2,
          39.13
        ],
        "value": 465
      },
      {
        "name": "河北省",
        "x": [
          113.04,
          36.01
        ],
        "value": 204
      },
      {
        "name": "山西省",
        "x": [
          112.53,
          37.87
        ],
        "value": 85
      },
      {
        "name": "内蒙古区",
        "x": [
          126.26,
          96.10
        ],
        "value": 72
      },
      {
        "name": "辽宁省",
        "x": [
          123.38,
          41.8
        ],
        "value": 1892
      },
      {
        "name": "吉林省",
        "x": [
          126.57,
          43.87
        ],
        "value": 900
      },
      {
        "name": "黑龙江省",
        "x": [
          126.63,
          45.75
        ],
        "value": 502
      },
      {
        "name": "上海市",
        "x": [
          121.48,
          31.22
        ],
        "value": 1479
      },
      {
        "name": "江苏省",
        "x": [
          118.78,
          32.04
        ],
        "value": 4844
      },
      {
        "name": "浙江省",
        "x": [
          121.56,
          29.86
        ],
        "value": 1492
      },
      {
        "name": "安徽省",
        "x": [
          117.27,
          31.68
        ],
        "value": 298
      },
      {
        "name": "福建省",
        "x": [
          120.2,
          26.89
        ],
        "value": 2563
      },
      {
        "name": "江西省",
        "x": [
          116.32,
          26.84
        ],
        "value": 113
      },
      {
        "name": "山东省",
        "x": [
          117.024,
          36.682
        ],
        "value": 3965
      },
      {
        "name": "河南省",
        "x": [
          113.65,
          34.76
        ],
        "value": 178
      },
      {
        "name": "湖北省",
        "x": [
          110.46,
          32.36
        ],
        "value": 2547
      },
      {
        "name": "湖南省",
        "x": [
          113.00,
          28.21
        ],
        "value": 355
      },
      {
        "name": "广东省",
        "x": [
          113.23,
          23.16
        ],
        "value": 3631
      },
      {
        "name": "广西区",
        "x": [
          108.33,
          22.84
        ],
        "value": 163
      },
      {
        "name": "海南省",
        "x": [
          110.72,
          19.61
        ],
        "value": 143
      },
      {
        "name": "重庆市",
        "x": [
          106.53,
          29.54
        ],
        "value": 1201
      },
      {
        "name": "四川省",
        "x": [
          104.06,
          30.67
        ],
        "value": 222
      },
      {
        "name": "贵州省",
        "x": [
          106.71,
          26.53
        ],
        "value": 91
      },
      {
        "name": "云南省",
        "x": [
          102.73,
          25.04
        ],
        "value": 1158
      },
      {
        "name": "陕西省",
        "x": [
          117.01,
          39.05
        ],
        "value": 580
      },
      {
        "name": "甘肃省",
        "x": [
          105.69,
          34.60
        ],
        "value": 93
      },
      {
        "name": "青海省",
        "x": [
          101.767921,
          36.6407
        ],
        "value": 15
      },
      {
        "name": "宁夏区",
        "x": [
          106.206,
          38.502
        ],
        "value": 51
      },
      {
        "name": "新疆区",
        "x": [
          87.68,
          43.77
        ],
        "value": 129
      }
    ]
  ],
  "company100": [
    [
      {
        "sort": 1,
        "name": "华为技术有限公司",
        "value": 2177.7227,
        "desc":"华为是全球领先的信息与通信技术（ICT）解决方案供应商，专注于ICT领域，坚持稳健经营、持续创新、开放合作，在电信运营商、企业、终端和云计算等领域构筑了端到端的解决方案优势",
        "x": [
          116.368714,
          39.912446
        ],
        "introduct": {
          "华为技术有限公司": [
            116.368714,
            39.912446
          ]
        }
      },
      {
        "sort": 2,
        "name": "海尔集团公司",
        "value": 432.102,
        "x": [
          120.33,
          36.07
        ],
        "introduct": {
          "海尔集团公司": [
            120.33,
            36.07
          ]
        }
      },
      {
        "sort": 3,
        "name": "浪潮集团有限公司",
        "value": 185.439,
        "x": [
          117,
          36.65
        ],
        "introduct": {
          "浪潮集团有限公司": [
            117,
            36.65
          ]
        }
      },
      {
        "sort": 4,
        "name": "杭州海康威视数字技术股份有限公司",
        "value": 151.7945,
        "x": [
          120.227282,
          30.215829
        ],
        "introduct": {
          "杭州海康威视数字技术股份有限公司": [
            120.227282,
            30.215829
          ]
        }
      },
      {
        "sort": 5,
        "name": "海信集团有限公司",
        "value": 118.6142,
        "x": [
          120.46,
          36.89
        ],
        "introduct": {
          "海信集团有限公司": [
            120.46,
            36.89
          ]
        }
      },
      {
        "sort": 6,
        "name": "南京南瑞集团公司",
        "value": 115.0419,
        "x": [
          116.295238,
          39.829332
        ],
        "introduct": {
          "南京南瑞集团公司": [
            116.295238,
            39.829332
          ]
        }
      },
      {
        "sort": 7,
        "name": "中国银联股份有限公司",
        "value": 112.0881,
        "x": [
          121.60487,
          31.517393
        ],
        "introduct": {
          "中国银联股份有限公司": [
            121.60487,
            31.517393
          ]
        }
      },
      {
        "sort": 8,
        "name": "国网信息通信产业集团有限公司",
        "value": 105.549,
        "x": [
          116.317821,
          40.07182
        ],
        "introduct": {
          "国网信息通信产业集团有限公司": [
            116.317821,
            40.07182
          ]
        }
      },
      {
        "sort": 9,
        "name": "浙江大华技术股份有限公司",
        "value": 104.7125,
        "x": [
          120.178958,
          30.3891
        ],
        "introduct": {
          "浙江大华技术股份有限公司": [
            120.178958,
            30.3891
          ]
        }
      },
      {
        "sort": 10,
        "name": "航天信息股份有限公司",
        "value": 94.5764,
        "x": [
          116.26427,
          39.952295
        ],
        "introduct": {
          "航天信息股份有限公司": [
            116.26427,
            39.952295
          ]
        }
      },
      {
        "sort": 11,
        "name": "株洲中车时代电气股份有限公司",
        "value": 80.858,
        "x": [
          113.131695,
          27.827433
        ],
        "introduct": {
          "株洲中车时代电气股份有限公司": [
            113.131695,
            27.827433
          ]
        }
      },
      {
        "sort": 12,
        "name": "华讯方舟科技有限公司",
        "value": 72.1596,
        "x": [
          113.971971,
          22.095078
        ],
        "introduct": {
          "华讯方舟科技有限公司": [
            113.971971,
            22.095078
          ]
        }
      },
      {
        "sort": 13,
        "name": "熊猫电子集团有限公司",
        "value": 69.5789,
        "x": [
          113.371971,
          22.595078
        ],
        "introduct": {
          "熊猫电子集团有限公司": [
            113.371971,
            22.595078
          ]
        }
      },
      {
        "sort": 14,
        "name": "阿里云计算有限公司",
        "value": 68.6886,
        "x": [
          120.090144,
          30.138649
        ],
        "introduct": {
          "阿里云计算有限公司": [
            120.090144,
            30.138649
          ]
        }
      },
      {
        "sort": 15,
        "name": "北京中软国际信息技术有限公司",
        "value": 68.2949,
        "x": [
          116.470272,
          39.889719
        ],
        "introduct": {
          "北京中软国际信息技术有限公司": [
            116.470272,
            39.889719
          ]
        }
      },
      {
        "sort": 16,
        "name": "北京京东尚科信息技术有限公司",
        "value": 67.6425,
        "x": [
          116.195645,
          39.929986
        ],
        "introduct": {
          "北京京东尚科信息技术有限公司": [
            116.195645,
            39.929986
          ]
        }
      },
      {
        "sort": 17,
        "name": "东华软件股份公司",
        "value": 67.1671,
        "x": [
          116.595645,
          39.129986
        ],
        "introduct": {
          "东华软件股份公司": [
            116.595645,
            39.129986
          ]
        }
      },
      {
        "sort": 18,
        "name": "东软集团股份有限公司",
        "value": 61.3112,
        "x": [
          116.430643,
          39.954631
        ],
        "introduct": {
          "东软集团股份有限公司": [
            116.430643,
            39.954631
          ]
        }
      },
      {
        "sort": 19,
        "name": "亚信科技（中国）有限公司",
        "value": 61.3089,
        "x": [
          104.184129,
          37.550339
        ],
        "introduct": {
          "亚信科技（中国）有限公司": [
            104.184129,
            37.550339
          ]
        }
      },
      {
        "sort": 20,
        "name": "软通动力信息技术（集团）有限公司",
        "value": 61.2716,
        "x": [
          116.27586,
          40.055524
        ],
        "introduct": {
          "软通动力信息技术（集团）有限公司": [
            116.27586,
            40.055524
          ]
        }
      },
      {
        "sort": 21,
        "name": "武汉邮电科学研究院",
        "value": 60.5081,
        "x": [
          114.397614,
          30.521235
        ],
        "introduct": {
          "武汉邮电科学研究院": [
            114.397614,
            30.521235
          ]
        }
      },
      {
        "sort": 22,
        "name": "同方股份有限公司",
        "value": 60.1402,
        "x": [
          116.345946,
          40.005377
        ],
        "introduct": {
          "同方股份有限公司": [
            116.345946,
            40.005377
          ]
        }
      },
      {
        "sort": 23,
        "name": "北京小米移动软件有限公司",
        "value": 59.7858,
        "x": [
          116.995645,
          39.329986
        ],
        "introduct": {
          "北京小米移动软件有限公司": [
            116.995645,
            39.329986
          ]
        }
      },
      {
        "sort": 24,
        "name": "新华三技术有限公司",
        "value": 58.3499,
        "x": [
          120.108151,
          30.645713
        ],
        "introduct": {
          "新华三技术有限公司": [
            120.108151,
            30.645713
          ]
        }
      },
      {
        "sort": 25,
        "name": "文思海辉技术有限公司",
        "value": 56.234,
        "x": [
          116.36308,
          40.050397
        ],
        "introduct": {
          "文思海辉技术有限公司": [
            116.36308,
            40.050397
          ]
        }
      },
      {
        "sort": 26,
        "name": "上海华东电脑股份有限公司",
        "value": 55.9629,
        "x": [
          121.421162,
          31.183996
        ],
        "introduct": {
          "上海华东电脑股份有限公司": [
            121.421162,
            31.183996
          ]
        }
      },
      {
        "sort": 27,
        "name": "江苏省通信服务有限公司",
        "value": 52.4848,
        "x": [
          118.78979,
          32.026292
        ],
        "introduct": {
          "江苏省通信服务有限公司": [
            118.78979,
            32.026292
          ]
        }
      },
      {
        "sort": 28,
        "name": "用友网络科技股份有限公司",
        "value": 49.8369,
        "x": [
          115.295645,
          39.229986
        ],
        "introduct": {
          "用友网络科技股份有限公司": [
            115.295645,
            39.229986
          ]
        }
      },
      {
        "sort": 29,
        "name": "福州福大自动化科技有限公司",
        "value": 47.3133,
        "x": [
          119.275157,
          26.029095
        ],
        "introduct": {
          "福州福大自动化科技有限公司": [
            119.275157,
            26.029095
          ]
        }
      },
      {
        "sort": 30,
        "name": "中国软件与技术服务股份有限公司",
        "value": 45.0188,
        "x": [
          116.34137,
          39.964123
        ],
        "introduct": {
          "中国软件与技术服务股份有限公司": [
            116.34137,
            39.964123
          ]
        }
      },
      {
        "sort": 31,
        "name": "北京全路通信信号研究设计院集团有限公司",
        "value": 44.9073,
        "x": [
          116.322819,
          39.883511
        ],
        "introduct": {
          "北京全路通信信号研究设计院集团有限公司": [
            116.322819,
            39.883511
          ]
        }
      },
      {
        "sort": 32,
        "name": "大族激光科技产业集团股份有限公司",
        "value": 44.0725,
        "x": [
          116.503584,
          39.77865
        ],
        "introduct": {
          "大族激光科技产业集团股份有限公司": [
            116.503584,
            39.77865
          ]
        }
      },
      {
        "sort": 33,
        "name": "广州佳都集团有限公司",
        "value": 43.0683,
        "x": [
          113.408584,
          23.130517
        ],
        "introduct": {
          "广州佳都集团有限公司": [
            113.408584,
            23.130517
          ]
        }
      },
      {
        "sort": 34,
        "name": "国电南京自动化股份有限公司",
        "value": 42.6174,
        "x": [
          116.778074,
          32.057236
        ],
        "introduct": {
          "国电南京自动化股份有限公司": [
            116.778074,
            32.057236
          ]
        }
      },
      {
        "sort": 35,
        "name": "浙大网新科技股份有限公司",
        "value": 40.9846,
        "x": [
          116.331107,
          39.959174
        ],
        "introduct": {
          "浙大网新科技股份有限公司": [
            116.331107,
            39.959174
          ]
        }
      },
      {
        "sort": 36,
        "name": "深圳市云中飞网络科技有限公司",
        "value": 40.4607,
        "x": [
          114.025974,
          22.246054
        ],
        "introduct": {
          "深圳市云中飞网络科技有限公司": [
            114.025974,
            22.246054
          ]
        }
      },
      {
        "sort": 37,
        "name": "上海华讯网络系统有限公司",
        "value": 40.1233,
        "x": [
          121.588612,
          33.210292
        ],
        "introduct": {
          "上海华讯网络系统有限公司": [
            121.588612,
            33.210292
          ]
        }
      },
      {
        "sort": 38,
        "name": "神州数码系统集成服务有限公司",
        "value": 40.0889,
        "x": [
          116.342658,
          39.95904
        ],
        "introduct": {
          "神州数码系统集成服务有限公司": [
            116.342658,
            39.95904
          ]
        }
      },
      {
        "sort": 39,
        "name": "上海宝信软件股份有限公司",
        "value": 39.5057,
        "x": [
          121.30487,
          31.617393
        ],
        "introduct": {
          "上海宝信软件股份有限公司": [
            121.30487,
            31.617393
          ]
        }
      },
      {
        "sort": 40,
        "name": "太极计算机股份有限公司",
        "value": 39.2637,
        "x": [
          116.380713,
          39.294563
        ],
        "introduct": {
          "太极计算机股份有限公司": [
            116.380713,
            39.294563
          ]
        }
      },
      {
        "sort": 41,
        "name": "中科软科技股份有限公司",
        "value": 36.8161,
        "x": [
          116.340482,
          39.990225
        ],
        "introduct": {
          "中科软科技股份有限公司": [
            116.340482,
            39.990225
          ]
        }
      },
      {
        "sort": 42,
        "name": "深圳市金证科技股份有限公司",
        "value": 36.2728,
        "x": [
          114.076138,
          22.541064
        ],
        "introduct": {
          "深圳市金证科技股份有限公司": [
            114.076138,
            22.541064
          ]
        }
      },
      {
        "sort": 43,
        "name": "中国电子科技网络信息安全有限公司",
        "value": 36.0107,
        "x": [
          116.305319,
          39.430809
        ],
        "introduct": {
          "中国电子科技网络信息安全有限公司": [
            116.305319,
            39.430809
          ]
        }
      },
      {
        "sort": 44,
        "name": "中国民航信息网络股份有限公司",
        "value": 35.6807,
        "x": [
          116.418454,
          39.93084
        ],
        "introduct": {
          "中国民航信息网络股份有限公司": [
            116.418454,
            39.93084
          ]
        }
      },
      {
        "sort": 45,
        "name": "中兴软创科技股份有限公司",
        "value": 35.156,
        "x": [
          115.778074,
          30.257236
        ],
        "introduct": {
          "中兴软创科技股份有限公司": [
            115.778074,
            30.257236
          ]
        }
      },
      {
        "sort": 46,
        "name": "福建星网锐捷通讯股份有限公司",
        "value": 33.8738,
        "x": [
          116.475157,
          27.129095
        ],
        "introduct": {
          "福建星网锐捷通讯股份有限公司": [
            116.475157,
            27.129095
          ]
        }
      },
      {
        "sort": 47,
        "name": "四川省通信产业服务有限公司",
        "value": 32.3302,
        "x": [
          102.89916,
          30.367481
        ],
        "introduct": {
          "四川省通信产业服务有限公司": [
            102.89916,
            30.367481
          ]
        }
      },
      {
        "sort": 48,
        "name": "平安科技（深圳）有限公司",
        "value": 32.3171,
        "x": [
          112.045974,
          22.146054
        ],
        "introduct": {
          "平安科技（深圳）有限公司": [
            112.045974,
            22.146054
          ]
        }
      },
      {
        "sort": 49,
        "name": "北明软件有限公司",
        "value": 32.2444,
        "x": [
          113.378584,
          23.430517
        ],
        "introduct": {
          "北明软件有限公司": [
            113.378584,
            23.430517
          ]
        }
      },
      {
        "sort": 50,
        "name": "科大讯飞股份有限公司",
        "value": 31.9531,
        "x": [
          117.282699,
          31.866942
        ],
        "introduct": {
          "科大讯飞股份有限公司": [
            117.282699,
            31.866942
          ]
        }
      },
      {
        "sort": 51,
        "name": "新大陆科技集团有限公司",
        "value": 31.183,
        "x": [
          119.215157,
          29.629095
        ],
        "introduct": {
          "新大陆科技集团有限公司": [
            119.215157,
            29.629095
          ]
        }
      },
      {
        "sort": 52,
        "name": "北京神州泰岳软件股份有限公司",
        "value": 30.3354,
        "x": [
          116.308124,
          39.974493
        ],
        "introduct": {
          "北京神州泰岳软件股份有限公司": [
            116.308124,
            39.974493
          ]
        }
      },
      {
        "sort": 53,
        "name": "广州广电运通金融电子股份有限公司",
        "value": 29.5442,
        "x": [
          113.453331,
          23.148727
        ],
        "introduct": {
          "广州广电运通金融电子股份有限公司": [
            113.453331,
            23.148727
          ]
        }
      },
      {
        "sort": 54,
        "name": "深圳市大疆创新科技有限公司",
        "value": 27.6548,
        "x": [
          113.571971,
          22.195078
        ],
        "introduct": {
          "深圳市大疆创新科技有限公司": [
            113.571971,
            22.195078
          ]
        }
      },
      {
        "sort": 55,
        "name": "石化盈科信息技术有限责任公司",
        "value": 27.4093,
        "x": [
          116.437404,
          39.938782
        ],
        "introduct": {
          "石化盈科信息技术有限责任公司": [
            116.437404,
            39.938782
          ]
        }
      },
      {
        "sort": 56,
        "name": "百度云计算技术(北京)有限公司",
        "value": 27.0973,
        "x": [
          116.280907,
          40.350259
        ],
        "introduct": {
          "百度云计算技术(北京)有限公司": [
            116.280907,
            40.350259
          ]
        }
      },
      {
        "sort": 57,
        "name": "广州海格通信集团股份有限公司",
        "value": 26.3627,
        "x": [
          113.4529,
          23.1504
        ],
        "introduct": {
          "广州海格通信集团股份有限公司": [
            113.4529,
            23.1504
          ]
        }
      },
      {
        "sort": 58,
        "name": "携程旅游网络技术(上海)有限公司",
        "value": 25.4201,
        "x": [
          121.487899,
          31.249162
        ],
        "introduct": {
          "携程旅游网络技术(上海)有限公司": [
            121.487899,
            31.249162
          ]
        }
      },
      {
        "sort": 59,
        "name": "卡斯柯信号有限公司",
        "value": 25.063,
        "x": [
          121.60487,
          31.817393
        ],
        "introduct": {
          "卡斯柯信号有限公司": [
            121.60487,
            31.817393
          ]
        }
      },
      {
        "sort": 60,
        "name": "中控科技集团有限公司",
        "value": 24.9671,
        "x": [
          116.318175,
          39.888275
        ],
        "introduct": {
          "中控科技集团有限公司": [
            116.318175,
            39.888275
          ]
        }
      },
      {
        "sort": 61,
        "name": "深圳天源迪科信息技术股份有限公司",
        "value": 24.4821,
        "x": [
          113.952885,
          22.339243
        ],
        "introduct": {
          "深圳天源迪科信息技术股份有限公司": [
            113.952885,
            22.339243
          ]
        }
      },
      {
        "sort": 62,
        "name": "东方电子集团有限公司",
        "value": 23.9469,
        "x": [
          113.052885,
          21.139243
        ],
        "introduct": {
          "东方电子集团有限公司": [
            113.052885,
            21.139243
          ]
        }
      },
      {
        "sort": 63,
        "name": "北京中油瑞飞信息技术有限责任公司",
        "value": 23.605,
        "x": [
          116.217133,
          39.90488
        ],
        "introduct": {
          "北京中油瑞飞信息技术有限责任公司": [
            116.217133,
            39.90488
          ]
        }
      },
      {
        "sort": 64,
        "name": "信雅达系统工程股份有限公司",
        "value": 23.3879,
        "x": [
          120.478958,
          30.6891
        ],
        "introduct": {
          "信雅达系统工程股份有限公司": [
            120.478958,
            30.6891
          ]
        }
      },
      {
        "sort": 65,
        "name": "深圳创维数字技术有限公司",
        "value": 22.7427,
        "x": [
          118.050663,
          22.605093
        ],
        "introduct": {
          "深圳创维数字技术有限公司": [
            118.050663,
            22.605093
          ]
        }
      },
      {
        "sort": 66,
        "name": "高德信息技术有限公司",
        "value": 22.2116,
        "x": [
          116.487575,
          39.695469
        ],
        "introduct": {
          "高德信息技术有限公司": [
            116.487575,
            39.695469
          ]
        }
      },
      {
        "sort": 67,
        "name": "银江股份有限公司",
        "value": 22.0552,
        "x": [
          120.140326,
          30.280157
        ],
        "introduct": {
          "银江股份有限公司": [
            120.140326,
            30.280157
          ]
        }
      },
      {
        "sort": 68,
        "name": "广东维沃软件技术有限公司",
        "value": 21.8287,
        "x": [
          113.648094,
          22.550698
        ],
        "introduct": {
          "广东维沃软件技术有限公司": [
            113.648094,
            22.550698
          ]
        }
      },
      {
        "sort": 69,
        "name": "北京千方科技股份有限公司",
        "value": 21.7299,
        "x": [
          116.395645,
          39.029986
        ],
        "introduct": {
          "北京千方科技股份有限公司": [
            116.395645,
            39.029986
          ]
        }
      },
      {
        "sort": 70,
        "name": "江苏金智集团有限公司",
        "value": 21.6804,
        "x": [
          119.468489,
          33.013797
        ],
        "introduct": {
          "江苏金智集团有限公司": [
            119.468489,
            33.013797
          ]
        }
      },
      {
        "sort": 71,
        "name": "恒生电子股份有限公司",
        "value": 21.588,
        "x": [
          121.188612,
          31.510292
        ],
        "introduct": {
          "恒生电子股份有限公司": [
            121.188612,
            31.510292
          ]
        }
      },
      {
        "sort": 72,
        "name": "四川九洲电器集团有限责任公司",
        "value": 21.3429,
        "x": [
          104.06,
          30.67
        ],
        "introduct": {
          "四川九洲电器集团有限责任公司": [
            104.06,
            30.67
          ]
        }
      },
      {
        "sort": 73,
        "name": "万达信息股份有限公司",
        "value": 20.7504,
        "x": [
          116.303724,
          39.919321
        ],
        "introduct": {
          "万达信息股份有限公司": [
            116.303724,
            39.919321
          ]
        }
      },
      {
        "sort": 74,
        "name": "杭州海兴电力科技股份有限公司",
        "value": 20.3609,
        "x": [
          120.608151,
          30.345713
        ],
        "introduct": {
          "杭州海兴电力科技股份有限公司": [
            120.608151,
            30.345713
          ]
        }
      },
      {
        "sort": 75,
        "name": "北京华胜天成科技股份有限公司",
        "value": 20.3235,
        "x": [
          116.335645,
          39.629986
        ],
        "introduct": {
          "北京华胜天成科技股份有限公司": [
            116.335645,
            39.629986
          ]
        }
      },
      {
        "sort": 76,
        "name": "广联达科技股份有限公司",
        "value": 20.2913,
        "x": [
          116.294602,
          40.057331
        ],
        "introduct": {
          "广联达科技股份有限公司": [
            116.294602,
            40.057331
          ]
        }
      },
      {
        "sort": 77,
        "name": "金蝶软件（中国）有限公司",
        "value": 20.1382,
        "x": [
          105.114129,
          37.880339
        ],
        "introduct": {
          "金蝶软件（中国）有限公司": [
            105.114129,
            37.880339
          ]
        }
      },
      {
        "sort": 78,
        "name": "浙江宇视科技有限公司",
        "value": 20.0728,
        "x": [
          120.58958,
          30.9191
        ],
        "introduct": {
          "浙江宇视科技有限公司": [
            120.58958,
            30.9191
          ]
        }
      },
      {
        "sort": 79,
        "name": "博彦科技股份有限公司",
        "value": 19.34,
        "x": [
          116.304311,
          40.05099
        ],
        "introduct": {
          "博彦科技股份有限公司": [
            116.304311,
            40.05099
          ]
        }
      },
      {
        "sort": 80,
        "name": "启明星辰信息技术集团股份有限公司",
        "value": 19.0514,
        "x": [
          116.917821,
          40.04182
        ],
        "introduct": {
          "启明星辰信息技术集团股份有限公司": [
            116.917821,
            40.04182
          ]
        }
      },
      {
        "sort": 81,
        "name": "先锋软件股份有限公司",
        "value": 18.8336,
        "x": [
          115.89,
          28.68
        ],
        "introduct": {
          "先锋软件股份有限公司": [
            115.89,
            28.68
          ]
        }
      },
      {
        "sort": 82,
        "name": "山东中创软件工程股份有限公司",
        "value": 18.6064,
        "x": [
          118.527663,
          36.09929
        ],
        "introduct": {
          "山东中创软件工程股份有限公司": [
            118.527663,
            36.09929
          ]
        }
      },
      {
        "sort": 83,
        "name": "北京华宇软件股份有限公司",
        "value": 18.2011,
        "x": [
          116.315645,
          38.929986
        ],
        "introduct": {
          "北京华宇软件股份有限公司": [
            116.315645,
            38.929986
          ]
        }
      },
      {
        "sort": 84,
        "name": "天津天地伟业数码科技有限公司",
        "value": 17.5025,
        "x": [
          117.210813,
          39.14393
        ],
        "introduct": {
          "天津天地伟业数码科技有限公司": [
            117.210813,
            39.14393
          ]
        }
      },
      {
        "sort": 85,
        "name": "北京易华录信息技术股份有限公司",
        "value": 17.3896,
        "x": [
          116.340153,
          39.199824
        ],
        "introduct": {
          "北京易华录信息技术股份有限公司": [
            116.340153,
            39.199824
          ]
        }
      },
      {
        "sort": 86,
        "name": "普天信息技术研究院有限公司",
        "value": 17.3202,
        "x": [
          116.317132,
          40.070105
        ],
        "introduct": {
          "普天信息技术研究院有限公司": [
            116.317132,
            40.070105
          ]
        }
      },
      {
        "sort": 87,
        "name": "和利时科技集团有限公司",
        "value": 17.2239,
        "x": [
          121.12,
          37.92
        ],
        "introduct": {
          "和利时科技集团有限公司": [
            121.12,
            37.92
          ]
        }
      },
      {
        "sort": 88,
        "name": "云南南天电子信息产业股份有限公司",
        "value": 17.0597,
        "x": [
          102.740681,
          25.039725
        ],
        "introduct": {
          "云南南天电子信息产业股份有限公司": [
            102.740681,
            25.039725
          ]
        }
      },
      {
        "sort": 89,
        "name": "大连华信计算机技术股份有限公司",
        "value": 16.9217,
        "x": [
          121.62,
          38.92
        ],
        "introduct": {
          "大连华信计算机技术股份有限公司": [
            121.62,
            38.92
          ]
        }
      },
      {
        "sort": 90,
        "name": "江苏润和科技投资集团有限公司",
        "value": 16.9174,
        "x": [
          119.368489,
          33.613797
        ],
        "introduct": {
          "江苏润和科技投资集团有限公司": [
            119.368489,
            33.613797
          ]
        }
      },
      {
        "sort": 91,
        "name": "北京立思辰科技股份有限公司",
        "value": 16.8973,
        "x": [
          116.395645,
          39.429986
        ],
        "introduct": {
          "北京立思辰科技股份有限公司": [
            116.395645,
            39.429986
          ]
        }
      },
      {
        "sort": 92,
        "name": "海能达通信股份有限公司",
        "value": 16.3956,
        "x": [
          115.025974,
          22.946054
        ],
        "introduct": {
          "海能达通信股份有限公司": [
            115.025974,
            22.946054
          ]
        }
      },
      {
        "sort": 93,
        "name": "中冶赛迪集团有限公司",
        "value": 16.279,
        "x": [
          106.55,
          29.57
        ],
        "introduct": {
          "中冶赛迪集团有限公司": [
            106.55,
            29.57
          ]
        }
      },
      {
        "sort": 94,
        "name": "北京宇信科技集团股份有限公司",
        "value": 16.2318,
        "x": [
          116.695645,
          39.929986
        ],
        "introduct": {
          "北京宇信科技集团股份有限公司": [
            116.695645,
            39.929986
          ]
        }
      },
      {
        "sort": 95,
        "name": "深圳怡化电脑股份有限公司",
        "value": 16.0138,
        "x": [
          117.025974,
          22.546054
        ],
        "introduct": {
          "深圳怡化电脑股份有限公司": [
            117.025974,
            22.546054
          ]
        }
      },
      {
        "sort": 96,
        "name": "北京四维图新科技股份有限公司",
        "value": 15.8531,
        "x": [
          116.461426,
          39.966684
        ],
        "introduct": {
          "北京四维图新科技股份有限公司": [
            116.461426,
            39.966684
          ]
        }
      },
      {
        "sort": 97,
        "name": "杭州士兰微电子股份有限公司",
        "value": 15.8081,
        "x": [
          120.640326,
          30.680157
        ],
        "introduct": {
          "杭州士兰微电子股份有限公司": [
            120.640326,
            30.680157
          ]
        }
      },
      {
        "sort": 98,
        "name": "南京联创科技集团股份有限公司",
        "value": 15.8027,
        "x": [
          118.778074,
          34.457236
        ],
        "introduct": {
          "南京联创科技集团股份有限公司": [
            118.778074,
            34.457236
          ]
        }
      },
      {
        "sort": 99,
        "name": "上海贝尔软件有限公司",
        "value": 14.5224,
        "x": [
          121.988612,
          31.210292
        ],
        "introduct": {
          "上海贝尔软件有限公司": [
            121.988612,
            31.210292
          ]
        }
      },
      {
        "sort": 100,
        "name": "北京四方继保自动化股份有限公司",
        "value": 14.5159,
        "x": [
          116.259996,
          40.07323
        ],
        "introduct": {
          "北京四方继保自动化股份有限公司": [
            116.259996,
            40.07323
          ]
        }
      }
    ]
  ],
  "regionLayout": [],
  "softwareCity": [
    [
      {"name":"南京","vlaue":1205,"year":"2010","x":[118.78, 32.04]},
      {"name":"济南","value":669.49,"year":"2011","x":[117, 36.65]},
      {"name":"成都","value":823.75,"year":"2012","x":[104.06, 30.67]},
      {"name":"广州","value":1128.1,"year":"2012","x":[113.23, 23.16]},
      {"name":"深圳","value":2015.64,"year":"2012","x": [114.07, 22.62]},
      {"name":"上海","value":1408.19,"year":"2013","x": [121.48, 31.22]},
      {"name":"北京","vlaue":2425.06,"year":"2013","x": [116.46, 39.92]},
      {"name":"福州","value":2004,"year":"2018","x": [119.3, 26.08]},
      {"name":"杭州","value":2004,"year":"2018","x": [120.19, 30.26]}
    ]
  ],
  "tryBase": [
    [
      { "name": "大连高新产业园区", "year": 2012,"x": [118.78,32.04]},
      { "name": "南京雨花软件园","year":2012,"x":[118.7773,31.98167]},
      { "name": "福州软件园","year":2012,"x":[119.2761,26.11895]},
     { "name": "齐鲁软件园","year":2012,"x":[117.1402,36.67863]},
     { "name": "青岛软件园","year":2012,"x":[120.4205,36.08222]},
     { "name": "广州天河软件园","year":2012,"x":[113.3792,23.12974]},
     { "name": "深圳软件园","year":2012,"x":[113.9456,22.55173]},
     { "name": "北京中关村科技园区海淀园","year":2012,"x":[116.3286,39.9667]},
     { "name": "软件和信息服务（智能语音）•合肥高新技术产业开发区","year":2012,"x":[117.2161,31.78441]},
     { "name": "上海浦东软件园","year":2013,"x":[121.6055,31.21364]},
     { "name": "厦门软件园","year":2013,"x":[118.1224,24.43638]},
     { "name": "武汉洪山区","year":2013,"x":[114.351,30.50882]},
     { "name": "天津滨海高新区软件园","year":2014,"x":[117.072,39.10116]},
     { "name": "上海紫竹高新技术产业开发区","year":2014,"x":[121.4574,31.03001]},
     { "name": "海南生态软件园","year":2014,"x":[110.1277,19.9525]},
     { "name": "西安高新区软件园","year":2014,"x":[108.8878,34.22994]},
     { "name": "上海市北高新技术服务业园区","year":2016,"x":[121.4439,31.30452]},
     { "name": "（大数据）•陕西西咸新区沣西","year":2015,"x":[108.7336,34.32204]}

    ],
    [
      { "name": "河北承德经济开发区","year":2018,"x":[117.9614,40.93069]},
      { "name": "内蒙古和林格尔新区","year":2018,"x":[111.8364,40.55716]},
      { "name": "上海静安区","year":2018,"x":[121.4504,31.23434]},
      { "name": "成都崇州","year":2018,"x":[103.6794,30.63684]}

    ]
  ],
  "softwarePark": [
    [
      {
        "name": "广东",
        "number": 4,
        "x": [
          113.23,
          23.16
        ]
      },
      {
        "name": "江苏",
        "number": 9,
        "x": [
          118.78,
          32.04
        ]
      },
      {
        "name": "北京",
        "number": 2,
        "x": [
          116.46,
          39.92
        ]
      },
      {
        "name": "浙江",
        "number": 9,
        "x": [
          121.56,
          29.86
        ]
      },
      {
        "name": "山东",
        "number": 2,
        "x": [
          117,
          36.69
        ]
      },
      {
        "name": "上海",
        "number": 3,
        "x": [
          121.48,
          31.22
        ]
      },
      {
        "name": "四川",
        "number": 1,
        "x": [
          104.06,
          30.67
        ]
      },
      {
        "name": "福建",
        "number": 2,
        "x": [
          120.2,
          26.89
        ]
      },
      {
        "name": "辽宁",
        "number": 2,
        "x": [
          123.38,
          41.8
        ]
      },
      {
        "name": "陕西",
        "number": 2,
        "x": [
          117.01,
          39.05
        ]
      },
      {
        "name": "湖北",
        "number": 2,
        "x": [
          110.46,
          32.36
        ]
      },
      {
        "name": "天津",
        "number": 2,
        "x": [
          117.2,
          39.13
        ]
      },
      {
        "name": "重庆",
        "number": 1,
        "x": [
          106.54,
          29.59
        ]
      },
      {
        "name": "湖南",
        "number": 1,
        "x": [
          113.00,
          28.21
        ]
      },
      {
        "name": "安徽",
        "number": 2,
        "x": [
          117.27,
          31.68
        ]
      },
      {
        "name": "吉林",
        "number": 1,
        "x": [
          126.57,
          43.87
        ]
      },
      {
        "name": "河北",
        "number": 2,
        "x": [
          113.04,
          36.01
        ]
      },
      {
        "name": "贵州",
        "number": 2,
        "x": [
          106.71,
          26.57
        ]
      },
      {
        "name": "广西",
        "number": 1,
        "x": [
          108.33,
          22.84
        ]
      },
      {
        "name": "海南",
        "number": 2,
        "x": [
          110.72,
          19.61
        ]
      },
      {
        "name": "黑龙江",
        "number": 1,
        "x": [
          126.63,
          45.75
        ]
      },
      {
        "name": "江西",
        "number": 1,
        "x": [
          116.32,
          26.84
        ]
      },
      {
        "name": "河南",
        "number": 1,
        "x": [
          113.65,
          34.76
        ]
      },
      {
        "name": "新疆",
        "number": 1,
        "x": [
          87.68,
          43.77
        ]
      },
      {
        "name": "甘肃",
        "number": 1,
        "x": [
          105.69,
          34.60
        ]
      },
      {
        "name": "内蒙古",
        "number": 1,
        "x": [
          126.26,
          96.10
        ]
      },
      {
        "name": "山西",
        "number": 1,
        "x": [
          112.53,
          37.87
        ]
      },
      {
        "name": "宁夏",
        "number": 1,
        "x": [
          106.27,
          38.47
        ]
      },
      {
        "name": "青海",
        "number": 0,
        "x": [
          101.74,
          36.56
        ]
      }
    ]
  ],
  "testPark": [
    [
      {
        "name": "广东",
        "value": 4330.7
      },
      {
        "name": "广州",
        "value": 4330.7
      },
      {
        "name": "珠海",
        "value": 4330.7
      },
      {
        "name": "香港",
        "value": 4330.7
      },
      {
        "name": "澳门",
        "value": 4330.7
      },
      {
        "name": "深圳",
        "value": 4330.7
      },
      {
        "name": "佛山",
        "value": 4330.7
      },
      {
        "name": "东莞",
        "value": 4330.7
      },
      {
        "name": "惠州",
        "value": 4330.7
      },
      {
        "name": "中山",
        "value": 4330.7
      },
      {
        "name": "江门",
        "value": 4330.7
      },
      {
        "name": "肇庆",
        "value": 4330.7
      },
      {
        "name": "北京",
        "value": 6640.9
      },

      {
        "name": "上海",
        "value": 1894.4
      },
      {
        "name": "天津",
        "value": 6640.9
      },
      {
        "name": "重庆",
        "value": 5452.0
      },


      {
        "name": "河北",
        "value": 5540.9
      },
      {
        "name": "贵州",
        "value": 6640.9
      },
      {
        "name": "河南",
        "value": 692.1
      },
     
      {
        "name": "内蒙古",
        "value": 161.6
      }  

    ]
  ],
  "testCity": [],
  "informationService": [
    [
      {
        "sort": 1.0,
        "name": "广东",
        "wanyuan": 3.4765713E7,
        "yiyuan": 3476.57,
        "x": [
          113.23,
          23.16
        ]
      },
      {
        "sort": 2.0,
        "name": "北京",
        "wanyuan": 3.3885526E7,
        "yiyuan": 3388.55,
        "x": [
          116.46,
          39.92
        ]
      },
      {
        "sort": 3.0,
        "name": "江苏",
        "wanyuan": 2.9870403E7,
        "yiyuan": 2987.04,
        "x": [
          118.78,
          32.04
        ]
      },
      {
        "sort": 4.0,
        "name": "浙江",
        "wanyuan": 1.9585955E7,
        "yiyuan": 1958.60,
        "x": [
          121.56,
          29.86
        ]
      },
      {
        "sort": 5.0,
        "name": "上海",
        "wanyuan": 1.95385E7,
        "yiyuan": 1953.85,
        "x": [
          121.48,
          31.22
        ]
      },
      {
        "sort": 6.0,
        "name": "山东",
        "wanyuan": 1.8173824E7,
        "yiyuan": 1817.38,
        "x": [
          117,
          36.69
        ]
      },
      {
        "sort": 7.0,
        "name": "四川",
        "wanyuan": 1.294031E7,
        "yiyuan": 1294.03,
        "x": [
          104.06,
          30.67
        ]
      },
      {
        "sort": 8.0,
        "name": "辽宁",
        "wanyuan": 1.1507739E7,
        "yiyuan": 1150.77,
        "x": [
          123.38,
          41.8
        ]
      },
      {
        "sort": 9.0,
        "name": "福建",
        "wanyuan": 1.1150965E7,
        "yiyuan": 1115.10,
        "x": [
          120.2,
          26.89
        ]
      },
      {
        "sort": 10.0,
        "name": "陕西",
        "wanyuan": 7648613.0,
        "yiyuan": 764.86,
        "x": [
          117.01,
          39.05
        ]
      },
      {
        "sort": 11.0,
        "name": "天津",
        "wanyuan": 5610324.0,
        "yiyuan": 561.03,
        "x": [
          117.2,
          39.13
        ]
      },
      {
        "sort": 12.0,
        "name": "重庆",
        "wanyuan": 5174932.0,
        "yiyuan": 517.49,
        "x": [
          106.54,
          29.59
        ]
      },
      {
        "sort": 13.0,
        "name": "湖北",
        "wanyuan": 5052722.0,
        "yiyuan": 505.27,
        "x": [
          110.46,
          32.36
        ]
      },
      {
        "sort": 14.0,
        "name": "吉林",
        "wanyuan": 2324938.0,
        "yiyuan": 232.49,
        "x": [
          126.57,
          43.87
        ]
      },
      {
        "sort": 15.0,
        "name": "湖南",
        "wanyuan": 1579648.0,
        "yiyuan": 157.96,
        "x": [
          113.00,
          28.21
        ]
      }
    ]
  ],
  "embededService": [
    [
      {
        "sort": 1.0,
        "name": "江苏",
        "wanyuan": 2.6089635E7,
        "yiyuan": 2608.96,
        "x": [
          118.78,
          32.04
        ]
      },
      {
        "sort": 2.0,
        "name": "广东",
        "wanyuan": 2.102822E7,
        "yiyuan": 2102.82,
        "x": [
          113.23,
          23.16
        ]
      },
      {
        "sort": 3.0,
        "name": "山东",
        "wanyuan": 6647112.0,
        "yiyuan": 664.71,
        "x": [
          117,
          36.69
        ]
      },
      {
        "sort": 4.0,
        "name": "浙江",
        "wanyuan": 3702882.0,
        "yiyuan": 370.29,
        "x": [
          121.56,
          29.86
        ]
      },
      {
        "sort": 5.0,
        "name": "福建",
        "wanyuan": 2304495.0,
        "yiyuan": 230.45,
        "x": [
          120.2,
          26.89
        ]
      },
      {
        "sort": 6.0,
        "name": "重庆",
        "wanyuan": 2084389.0,
        "yiyuan": 208.44,
        "x": [
          106.54,
          29.59
        ]
      },
      {
        "sort": 7.0,
        "name": "天津",
        "wanyuan": 1910200.0,
        "yiyuan": 191.02,
        "x": [
          117.2,
          39.13
        ]
      },
      {
        "sort": 8.0,
        "name": "陕西",
        "wanyuan": 1259624.0,
        "yiyuan": 125.96,
        "x": [
          117.01,
          39.05
        ]
      },
      {
        "sort": 9.0,
        "name": "上海",
        "wanyuan": 1200000.0,
        "yiyuan": 120.00,
        "x": [
          121.48,
          31.22
        ]
      },
      {
        "sort": 10.0,
        "name": "辽宁",
        "wanyuan": 1050425.0,
        "yiyuan": 105.04,
        "x": [
          123.38,
          41.8
        ]
      },
      {
        "sort": 11.0,
        "name": "北京",
        "wanyuan": 988089.0,
        "yiyuan": 98.81,
        "x": [
          116.46,
          39.92
        ]
      },
      {
        "sort": 12.0,
        "name": "吉林",
        "wanyuan": 930955.0,
        "yiyuan": 93.10,
        "x": [
          126.57,
          43.87
        ]
      },
      {
        "sort": 13.0,
        "name": "湖北",
        "wanyuan": 624014.0,
        "yiyuan": 62.40,
        "x": [
          110.46,
          32.36
        ]
      },
      {
        "sort": 14.0,
        "name": "四川",
        "wanyuan": 478240.0,
        "yiyuan": 47.82,
        "x": [
          104.06,
          30.67
        ]
      },
      {
        "sort": 15.0,
        "name": "湖南",
        "wanyuan": 415798.0,
        "yiyuan": 41.58,
        "x": [
          113.00,
          28.21
        ]
      },
      {
        "sort": 16.0,
        "name": "安徽",
        "wanyuan": 245629.0,
        "yiyuan": 24.56,
        "x": [
          117.27,
          31.68
        ]
      },
      {
        "sort": 17.0,
        "name": "黑龙江",
        "wanyuan": 142049.0,
        "yiyuan": 14.20,
        "x": [
          126.63,
          45.75
        ]
      },
      {
        "sort": 18.0,
        "name": "河南",
        "wanyuan": 119205.0,
        "yiyuan": 11.92,
        "x": [
          113.65,
          34.76
        ]
      },
      {
        "sort": 19.0,
        "name": "河北",
        "wanyuan": 90001.0,
        "yiyuan": 9.00,
        "x": [
          113.04,
          36.01
        ]
      },
      {
        "sort": 20.0,
        "name": "山西",
        "wanyuan": 19018.0,
        "yiyuan": 1.90,
        "x": [
          112.53,
          37.87
        ]
      },
      {
        "sort": 21.0,
        "name": "江西",
        "wanyuan": 13589.0,
        "yiyuan": 1.36,
        "x": [
          116.32,
          26.84
        ]
      },
      {
        "sort": 22.0,
        "name": "宁夏",
        "wanyuan": 13088.0,
        "yiyuan": 1.31,
        "x": [
          106.27,
          38.47
        ]
      },
      {
        "sort": 23.0,
        "name": "贵州",
        "wanyuan": 7825.0,
        "yiyuan": 0.78,
        "x": [
          106.71,
          26.53
        ]
      },
      {
        "sort": 24.0,
        "name": "广西",
        "wanyuan": 5105.0,
        "yiyuan": 0.51,
        "x": [
          108.33,
          22.84
        ]
      },
      {
        "sort": 25.0,
        "name": "新疆",
        "wanyuan": 4305.0,
        "yiyuan": 0.43,
        "x": [
          87.68,
          43.77
        ]
      },
      {
        "sort": 26.0,
        "name": "新疆兵团",
        "wanyuan": 4305.0,
        "yiyuan": 0.43,
        "x": [
          87.68,
          43.77
        ]
      },
      {
        "sort": 27.0,
        "name": "甘肃",
        "wanyuan": 3947.0,
        "yiyuan": 0.39,
        "x": [
          105.69,
          34.60
        ]
      },
      {
        "sort": 28.0,
        "name": "云南",
        "wanyuan": 2840.0,
        "yiyuan": 0.28,
        "x": [
          102.73,
          25.04
        ]
      },
      {
        "sort": 29.0,
        "name": "内蒙古",
        "wanyuan": 1610.0,
        "yiyuan": 0.16,
        "x": [
          126.26,
          96.10
        ]
      },
      {
        "sort": 30.0,
        "name": "海南",
        "wanyuan": 1017.0,
        "yiyuan": 0.10,
        "x": [
          110.72,
          19.61
        ]
      }
    ]
  ],
  "seriesData": [
    [
      9301.77,
      13301.47,
      17301.77,
      18201.34,
      21201.23
    ],
    [
      1059.35,
      2757.67,
      4577.85,
      5558.65,
      6557.85
    ]
  ]
}